django_cognito_jwt2/__init__.py
django_cognito_jwt2/backend.py
django_cognito_jwt2/validator.py
django_cognito_jwt2-0.2.0.dist-info/LICENSE
django_cognito_jwt2-0.2.0.dist-info/METADATA
django_cognito_jwt2-0.2.0.dist-info/WHEEL
django_cognito_jwt2-0.2.0.dist-info/top_level.txt
django_cognito_jwt2-0.2.0.dist-info/RECORD
