Metadata-Version: 2.1
Name: django-cognito-jwt2
Version: 0.2.0
Summary: Django backends for AWS Cognito JWT
Home-page: https://github.com/bekindsoft/django-cognito-jwt2
Author: Essau Ramirez, Michael van Tellingen
Author-email: essau@bekind.software, m.vantellingen@labdigital.nl
License: MIT
Classifier: Development Status :: 5 - Production/Stable
Classifier: Environment :: Web Environment
Classifier: Framework :: Django
Classifier: Framework :: Django :: 4.2
Classifier: Framework :: Django :: 5.2
Classifier: License :: OSI Approved :: MIT License
Classifier: Programming Language :: Python
Classifier: Programming Language :: Python :: 3
Classifier: Programming Language :: Python :: 3.11
Classifier: Programming Language :: Python :: 3.12
Classifier: Programming Language :: Python :: 3.13
License-File: LICENSE
Requires-Dist: Django>=4.2
Requires-Dist: cryptography
Requires-Dist: djangorestframework
Requires-Dist: pyjwt
Requires-Dist: requests
Requires-Dist: django-ninja>=1.0.0
Provides-Extra: docs
Requires-Dist: sphinx>=1.4.0; extra == "docs"
Provides-Extra: test
Requires-Dist: coverage[toml]==7.8.2; extra == "test"
Requires-Dist: pytest==8.4.0; extra == "test"
Requires-Dist: pytest-django==4.11.1; extra == "test"
Requires-Dist: pytest-cov==6.1.1; extra == "test"
Requires-Dist: pytest-responses==0.5.1; extra == "test"
Requires-Dist: isort[pyproject]==4.3.21; extra == "test"
Requires-Dist: flake8==3.7.9; extra == "test"
Requires-Dist: flake8-imports==0.1.1; extra == "test"
Requires-Dist: flake8-blind-except==0.1.1; extra == "test"
Requires-Dist: flake8-debugger==3.1.0; extra == "test"
